saltext/salt_describe/__init__.py
saltext/salt_describe/version.py
saltext/salt_describe/runners/__init__.py
saltext/salt_describe/runners/salt_describe.py
saltext/salt_describe/runners/salt_describe_cron.py
saltext/salt_describe/runners/salt_describe_file.py
saltext/salt_describe/runners/salt_describe_firewalld.py
saltext/salt_describe/runners/salt_describe_host.py
saltext/salt_describe/runners/salt_describe_iptables.py
saltext/salt_describe/runners/salt_describe_pip.py
saltext/salt_describe/runners/salt_describe_pkg.py
saltext/salt_describe/runners/salt_describe_pkgrepo.py
saltext/salt_describe/runners/salt_describe_service.py
saltext/salt_describe/runners/salt_describe_sysctl.py
saltext/salt_describe/runners/salt_describe_timezone.py
saltext/salt_describe/runners/salt_describe_user.py
saltext/salt_describe/utils/ansible_describe.py
saltext/salt_describe/utils/chef_describe.py
saltext/salt_describe/utils/init.py
saltext/salt_describe/utils/salt_describe.py
saltext.salt_describe-1.0.0.dist-info/LICENSE
saltext.salt_describe-1.0.0.dist-info/METADATA
saltext.salt_describe-1.0.0.dist-info/NOTICE
saltext.salt_describe-1.0.0.dist-info/WHEEL
saltext.salt_describe-1.0.0.dist-info/entry_points.txt
saltext.salt_describe-1.0.0.dist-info/top_level.txt
saltext.salt_describe-1.0.0.dist-info/RECORD
